venvtools/__init__.py
venvtools/extended_env_builder.py
venvtools/py.typed
venvtools/virtual_env_command.py
venvtools-1.0.1.dist-info/LICENSE
venvtools-1.0.1.dist-info/METADATA
venvtools-1.0.1.dist-info/WHEEL
venvtools-1.0.1.dist-info/entry_points.txt
venvtools-1.0.1.dist-info/top_level.txt
venvtools-1.0.1.dist-info/zip-safe
venvtools-1.0.1.dist-info/RECORD
