Metadata-Version: 2.1
Name: venvtools
Version: 1.0.1
Summary: A simple setuptools command to help with virtualenv
Home-page: https://github.com/HeavenVolkoff/venvtools
Author: Vítor Vasconcellos
Author-email: vasconcellos.dev@gmail.com
Maintainer: Vítor Vasconcellos
Maintainer-email: vasconcellos.dev@gmail.com
License: BSD-3-Clause
Download-URL: https://github.com/HeavenVolkoff/venvtools/archive/master.zip
Project-URL: Source Code, https://github.com/HeavenVolkoff/venvtools
Project-URL: Bug Tracker, https://github.com/HeavenVolkoff/venvtools/issues
Keywords: venv,command,distutils,setuptools
Platform: UNKNOWN
Classifier: Framework :: Setuptools Plugin
Classifier: Development Status :: 5 - Production/Stable
Classifier: Programming Language :: Python :: 3 :: Only
Classifier: Programming Language :: Python :: 3.6
Classifier: Programming Language :: Python :: 3.7
Classifier: Programming Language :: Python :: 3.8
Classifier: Programming Language :: Python :: 3.9
Classifier: License :: OSI Approved :: BSD License
Requires-Python: ~=3.6
Requires-Dist: pip (>=20.3)
Requires-Dist: setuptools (>=45.0.0)
Requires-Dist: typing-extensions ; python_version < "3.8"
Requires-Dist: importlib-metadata ; python_version < "3.8"
Provides-Extra: dev
Requires-Dist: twine ; extra == 'dev'
Requires-Dist: black ; extra == 'dev'
Requires-Dist: isort (~=5.0) ; extra == 'dev'
Provides-Extra: docs
Provides-Extra: tests
Requires-Dist: mypy ; extra == 'tests'
